README.rst
setup.cfg
setup.py
randassign/__init__.py
randassign/fmtversion.py
randassign/latex.py
randassign/make.py
randassign/version.py
randassign.egg-info/PKG-INFO
randassign.egg-info/SOURCES.txt
randassign.egg-info/dependency_links.txt
randassign.egg-info/entry_points.txt
randassign.egg-info/top_level.txt
test/test_latex.py
test/test_make.py