Metadata-Version: 1.1
Name: randassign
Version: 1.0.1
Summary: Create randomized assignments with PythonTeX
Home-page: http://github.com/gpoore/randassign
Author: Geoffrey M. Poore
Author-email: gpoore@gmail.com
License: BSD
Keywords: education,PythonTeX
Platform: UNKNOWN
Classifier: Development Status :: 5 - Production/Stable
Classifier: Environment :: Console
Classifier: Intended Audience :: Education
Classifier: License :: OSI Approved :: BSD License
Classifier: Operating System :: OS Independent
Classifier: Programming Language :: Python
Classifier: Programming Language :: Python :: 2
Classifier: Programming Language :: Python :: 3
Classifier: Topic :: Education
Classifier: Topic :: Education :: Testing
